rn_simplex/simplex.py
rn_simplex/test_simplex.py
rn_simplex-2021.5.dist-info/METADATA
rn_simplex-2021.5.dist-info/WHEEL
rn_simplex-2021.5.dist-info/top_level.txt
rn_simplex-2021.5.dist-info/RECORD
