Metadata-Version: 2.1
Name: rn-simplex
Version: 2021.5
Summary: Regular N-dimensional Simplex Builder
Home-page: https://gitlab.inria.fr/edebreuv/rn-simplex
Author: Eric Debreuve
Author-email: eric.debreuve@univ-cotedazur.fr
License: UNKNOWN
Project-URL: Source, https://gitlab.inria.fr/edebreuv/rn-simplex
Keywords: geometry,polytope,simplex
Platform: UNKNOWN
Classifier: Topic :: Scientific/Engineering :: Mathematics
Classifier: Intended Audience :: Science/Research
Classifier: License :: OSI Approved :: CEA CNRS Inria Logiciel Libre License, version 2.1 (CeCILL-2.1)
Classifier: Programming Language :: Python :: 3.8
Classifier: Development Status :: 4 - Beta
Requires-Python: >=3.8
Requires-Dist: matplotlib
Requires-Dist: miniball
Requires-Dist: numpy
Requires-Dist: scipy
